cbptools/__init__.py
cbptools/_version.py
cbptools/clean.py
cbptools/cluster.py
cbptools/connectivity.py
cbptools/exceptions.py
cbptools/image.py
cbptools/main.py
cbptools/plotting.py
cbptools/project.py
cbptools/schema.yaml
cbptools/utils.py
cbptools/validation.py
cbptools/workflow.py
cbptools/tasks/__init__.py
cbptools/tasks/clustering.py
cbptools/tasks/connectivity.py
cbptools/tasks/masks.py
cbptools/tasks/plotting.py
cbptools/tasks/validity.py
cbptools/templates/MNI152GM.nii.gz
cbptools-1.1.6.dist-info/LICENSE
cbptools-1.1.6.dist-info/METADATA
cbptools-1.1.6.dist-info/WHEEL
cbptools-1.1.6.dist-info/entry_points.txt
cbptools-1.1.6.dist-info/top_level.txt
cbptools-1.1.6.dist-info/RECORD
