Metadata-Version: 2.1
Name: cbptools
Version: 1.1.6
Summary: Regional Connectivity-Based Parcellation tool for Python
Home-page: https://github.com/inm7/cbptools
Author: Niels Reuter
Author-email: niels.reuter@gmail.com
License: Apache
Platform: UNKNOWN
Requires-Python: >=3.5.0
Requires-Dist: matplotlib (==3.0.3)
Requires-Dist: nibabel (>=2.5.0)
Requires-Dist: numpy (>=1.17.0)
Requires-Dist: pandas (>=0.25.0)
Requires-Dist: pyyaml (>=5.1.1)
Requires-Dist: scikit-learn (>=0.21.3)
Requires-Dist: scipy (>=1.3.0)
Requires-Dist: seaborn (>=0.9.0)
Requires-Dist: snakemake (>=5.5.4)
Provides-Extra: devel-docs
Requires-Dist: pypandoc ; extra == 'devel-docs'
